fasthtml/__init__.py
fasthtml/_modidx.py
fasthtml/authmw.py
fasthtml/basics.py
fasthtml/cli.py
fasthtml/common.py
fasthtml/components.py
fasthtml/components.pyi
fasthtml/core.py
fasthtml/core.pyi
fasthtml/fastapp.py
fasthtml/ft.py
fasthtml/js.py
fasthtml/jupyter.py
fasthtml/katex.js
fasthtml/live_reload.py
fasthtml/oauth.py
fasthtml/pico.py
fasthtml/starlette.py
fasthtml/stripe_otp.py
fasthtml/svg.py
fasthtml/toaster.py
fasthtml/xtend.py
fasthtml/xtend.pyi
python_fasthtml-0.12.37.dist-info/licenses/LICENSE
python_fasthtml-0.12.37.dist-info/METADATA
python_fasthtml-0.12.37.dist-info/WHEEL
python_fasthtml-0.12.37.dist-info/entry_points.txt
python_fasthtml-0.12.37.dist-info/top_level.txt
python_fasthtml-0.12.37.dist-info/RECORD
