Metadata-Version: 2.4
Name: python-fasthtml
Version: 0.12.37
Summary: The fastest way to create an HTML app
Home-page: https://github.com/AnswerDotAI/fasthtml
Author: Jeremy Howard and contributors
Author-email: github@jhoward.fastmail.fm
License: Apache Software License 2.0
Keywords: nbdev jupyter notebook python
Classifier: Development Status :: 4 - Beta
Classifier: Intended Audience :: Developers
Classifier: Natural Language :: English
Classifier: Programming Language :: Python :: 3.10
Classifier: Programming Language :: Python :: 3.11
Classifier: Programming Language :: Python :: 3.12
Classifier: Programming Language :: Python :: 3.13
Classifier: License :: OSI Approved :: Apache Software License
Requires-Python: >=3.10
License-File: LICENSE
Requires-Dist: fastcore>=1.10.0
Requires-Dist: python-dateutil
Requires-Dist: starlette>0.33
Requires-Dist: oauthlib
Requires-Dist: itsdangerous
Requires-Dist: uvicorn[standard]>=0.30
Requires-Dist: httpx
Requires-Dist: fastlite>=0.1.1
Requires-Dist: python-multipart
Requires-Dist: beautifulsoup4
Provides-Extra: dev
Requires-Dist: ipython; extra == "dev"
Requires-Dist: lxml; extra == "dev"
Requires-Dist: pysymbol_llm; extra == "dev"
Requires-Dist: monsterui; extra == "dev"
Requires-Dist: PyJWT; extra == "dev"
Dynamic: author
Dynamic: author-email
Dynamic: classifier
Dynamic: description
Dynamic: description-content-type
Dynamic: home-page
Dynamic: keywords
Dynamic: license
Dynamic: license-file
Dynamic: provides-extra
Dynamic: requires-dist
Dynamic: requires-python
Dynamic: summary
